[
  {
    "verse": 1,
    "text": " De cierto, de cierto os digo: El que no entra por la puerta en el redil de las ovejas, sino que sube por otra parte, ese es ladrón y salteador."
  },
  {
    "verse": 2,
    "text": " Mas el que entra por la puerta, el pastor de las ovejas es."
  },
  {
    "verse": 3,
    "text": " A este abre el portero, y las ovejas oyen su voz; y a sus ovejas llama por nombre, y las saca."
  },
  {
    "verse": 4,
    "text": " Y cuando ha sacado fuera todas las propias, va delante de ellas; y las ovejas le siguen, porque conocen su voz."
  },
  {
    "verse": 5,
    "text": " Mas al extraño no seguirán, sino huirán de él, porque no conocen la voz de los extraños."
  },
  {
    "verse": 6,
    "text": " Esta alegoría les dijo Jesús; pero ellos no entendieron qué era lo que les decía."
  },
  {
    "verse": 7,
    "text": " Volvió, pues, Jesús a decirles: De cierto, de cierto os digo: Yo soy la puerta de las ovejas."
  },
  {
    "verse": 8,
    "text": " Todos los que antes de mí vinieron, ladrones son y salteadores; pero no los oyeron las ovejas."
  },
  {
    "verse": 9,
    "text": " Yo soy la puerta; el que por mí entrare, será salvo; y entrará, y saldrá, y hallará pastos."
  },
  {
    "verse": 10,
    "text": " El ladrón no viene sino para hurtar y matar y destruir; yo he venido para que tengan vida, y para que la tengan en abundancia."
  },
  {
    "verse": 11,
    "text": " Yo soy el buen pastor; el buen pastor su vida da por las ovejas."
  },
  {
    "verse": 12,
    "text": " Mas el asalariado, y que no es el pastor, de quien no son propias las ovejas, ve venir al lobo y deja las ovejas y huye, y el lobo arrebata las ovejas y las dispersa."
  },
  {
    "verse": 13,
    "text": " Así que el asalariado huye, porque es asalariado, y no le importan las ovejas."
  },
  {
    "verse": 14,
    "text": " Yo soy el buen pastor; y conozco mis ovejas, y las mías me conocen,"
  },
  {
    "verse": 15,
    "text": " así como el Padre me conoce, y yo conozco al Padre; y pongo mi vida por las ovejas."
  },
  {
    "verse": 16,
    "text": " También tengo otras ovejas que no son de este redil; aquellas también debo traer, y oirán mi voz; y habrá un rebaño, y un pastor."
  },
  {
    "verse": 17,
    "text": " Por eso me ama el Padre, porque yo pongo mi vida, para volverla a tomar."
  },
  {
    "verse": 18,
    "text": " Nadie me la quita, sino que yo de mí mismo la pongo. Tengo poder para ponerla, y tengo poder para volverla a tomar. Este mandamiento recibí de mi Padre."
  },
  {
    "verse": 19,
    "text": " Volvió a haber disensión entre los judíos por estas palabras."
  },
  {
    "verse": 20,
    "text": " Muchos de ellos decían: Demonio tiene, y está fuera de sí; ¿por qué le oís?"
  },
  {
    "verse": 21,
    "text": " Decían otros: Estas palabras no son de endemoniado. ¿Puede acaso el demonio abrir los ojos de los ciegos?"
  },
  {
    "verse": 22,
    "text": " Celebrábase en Jerusalén la fiesta de la dedicación. Era invierno,"
  },
  {
    "verse": 23,
    "text": " y Jesús andaba en el templo por el pórtico de Salomón."
  },
  {
    "verse": 24,
    "text": " Y le rodearon los judíos y le dijeron: ¿Hasta cuándo nos turbarás el alma? Si tú eres el Cristo, dínoslo abiertamente."
  },
  {
    "verse": 25,
    "text": " Jesús les respondió: Os lo he dicho, y no creéis; las obras que yo hago en nombre de mi Padre, ellas dan testimonio de mí;"
  },
  {
    "verse": 26,
    "text": " pero vosotros no creéis, porque no sois de mis ovejas, como os he dicho."
  },
  {
    "verse": 27,
    "text": " Mis ovejas oyen mi voz, y yo las conozco, y me siguen,"
  },
  {
    "verse": 28,
    "text": " y yo les doy vida eterna; y no perecerán jamás, ni nadie las arrebatará de mi mano."
  },
  {
    "verse": 29,
    "text": " Mi Padre que me las dio, es mayor que todos, y nadie las puede arrebatar de la mano de mi Padre."
  },
  {
    "verse": 30,
    "text": " Yo y el Padre uno somos."
  },
  {
    "verse": 31,
    "text": " Entonces los judíos volvieron a tomar piedras para apedrearle."
  },
  {
    "verse": 32,
    "text": " Jesús les respondió: Muchas buenas obras os he mostrado de mi Padre; ¿por cuál de ellas me apedreáis?"
  },
  {
    "verse": 33,
    "text": " Le respondieron los judíos, diciendo: Por buena obra no te apedreamos, sino por la blasfemia; porque tú, siendo hombre, te haces Dios."
  },
  {
    "verse": 34,
    "text": " Jesús les respondió: ¿No está escrito en vuestra ley: Yo dije, dioses sois?"
  },
  {
    "verse": 35,
    "text": " Si llamó dioses a aquellos a quienes vino la palabra de Dios (y la Escritura no puede ser quebrantada),"
  },
  {
    "verse": 36,
    "text": " ¿al que el Padre santificó y envió al mundo, vosotros decís: Tú blasfemas, porque dije: Hijo de Dios soy?"
  },
  {
    "verse": 37,
    "text": " Si no hago las obras de mi Padre, no me creáis."
  },
  {
    "verse": 38,
    "text": " Mas si las hago, aunque no me creáis a mí, creed a las obras, para que conozcáis y creáis que el Padre está en mí, y yo en el Padre."
  },
  {
    "verse": 39,
    "text": " Procuraron otra vez prenderle, pero él se escapó de sus manos."
  },
  {
    "verse": 40,
    "text": " Y se fue de nuevo al otro lado del Jordán, al lugar donde primero había estado bautizando Juan; y se quedó allí."
  },
  {
    "verse": 41,
    "text": " Y muchos venían a él, y decían: Juan, a la verdad, ninguna señal hizo; pero todo lo que Juan dijo de este, era verdad."
  },
  {
    "verse": 42,
    "text": " Y muchos creyeron en él allí."
  }
]